README.rst
setup.py
WeChat_OAuth2.egg-info/PKG-INFO
WeChat_OAuth2.egg-info/SOURCES.txt
WeChat_OAuth2.egg-info/dependency_links.txt
WeChat_OAuth2.egg-info/requires.txt
WeChat_OAuth2.egg-info/top_level.txt
wechat_oauth2/__about__.py
wechat_oauth2/__init__.py
wechat_oauth2.egg-info/PKG-INFO
wechat_oauth2.egg-info/SOURCES.txt
wechat_oauth2.egg-info/dependency_links.txt
wechat_oauth2.egg-info/requires.txt
wechat_oauth2.egg-info/top_level.txt