Metadata-Version: 1.0
Name: WeChat-OAuth2
Version: 0.1.2
Summary: wechat sdk
Home-page: https://github.com/codeif/WeChat-OAuth2
Author: codeif
Author-email: me@codeif.com
License: MIT
Platform: UNKNOWN
